Metadata-Version: 2.1
Name: spec2chat
Version: 0.1.7
Summary: API-driven chatbot generation from OpenAPI service specifications
Home-page: https://github.com/mjesusrodriguez/spec2chat
Author: María Jesús Rodríguez Sánchez
Author-email: María Jesús Rodríguez Sánchez <mjesusrodriguez@ugr.es>
License: Apache-2.0
Classifier: Programming Language :: Python :: 3
Classifier: License :: OSI Approved :: Apache Software License
Classifier: Operating System :: OS Independent
Requires-Python: >=3.8
License-File: LICENSE
Requires-Dist: openai (>=0.27.0)
Requires-Dist: pymongo (<5.0.0,>=4.0.0)
Requires-Dist: spacy (==3.7.2)
Requires-Dist: nltk (>=3.7)
Requires-Dist: python-dotenv (>=0.21.0)
Requires-Dist: dnspython
Requires-Dist: setuptools (>=65.0.0)
